squiffy/__init__.py
squiffy/application.py
squiffy/errors.py
squiffy/screen.py
squiffy/signals.py
squiffy/state.py
squiffy/utils.py
squiffy/version.py
squiffy/abstract/__init__.py
squiffy/abstract/abstract_application.py
squiffy/abstract/abstract_context.py
squiffy/abstract/abstract_layout.py
squiffy/abstract/abstract_menu.py
squiffy/abstract/abstract_state.py
squiffy/abstract/abstract_style.py
squiffy/context/__init__.py
squiffy/context/context.py
squiffy/context/executor.py
squiffy/example/__init__.py
squiffy/example/ex_layout.json
squiffy/example/example.py
squiffy/layout/__init__.py
squiffy/layout/borders.py
squiffy/layout/contants.py
squiffy/layout/layout_factory.py
squiffy/layout/style.py
squiffy/layout/style_components.py
squiffy/layout/style_factory.py
squiffy/menu/__init__.py
squiffy/menu/error_submenu.py
squiffy/menu/menu.py
squiffy/menu/menu_events.py
squiffy/menu/menu_items.py
squiffy/menu/menu_layers.py
squiffy/menu/menu_observers.py
squiffy/menu/submenu.py
squiffy-0.1.4.dist-info/METADATA
squiffy-0.1.4.dist-info/WHEEL
squiffy-0.1.4.dist-info/licenses/LICENSE
squiffy-0.1.4.dist-info/RECORD
