Metadata-Version: 2.3
Name: squiffy
Version: 0.1.4
Summary: Squiffy is the minimal library that helps you build your CLI application before your boss notices
Project-URL: Repository, https://github.com/Gygarte/squiffy.git
Project-URL: Changelog, https://github.com/Gygarte/squiffy/blob/main/CHANGELOG.md
Author-email: Gabriel Artemie <gabriel.artemie@gmail.com>
License: MIT License
License-File: LICENSE
Keywords: CLI application,cli,console,console menu,menu,minimal,terminal
Classifier: Development Status :: 3 - Alpha
Classifier: Intended Audience :: Developers
Classifier: License :: OSI Approved :: MIT License
Classifier: Operating System :: Microsoft :: Windows
Classifier: Programming Language :: Python :: 3
Classifier: Programming Language :: Python :: 3.12
Requires-Python: >=3.8
Requires-Dist: markdown-it-py==3.0.0
Requires-Dist: mdurl==0.1.2
Requires-Dist: prompt-toolkit==3.0.47
Requires-Dist: pygments==2.18.0
Requires-Dist: rich==13.7.1
Requires-Dist: wcwidth==0.2.13
